{"id": "inbenta", "name": "Inbenta", "category": "site_analytics", "website_url": "https://www.inbenta.com/en/", "ghostery_id": null, "company_id": "inbenta", "company_name": "Inbenta", "iab_vendor": null, "truste_type": null, "description": null, "truste_privacy_url": null, "privacy_url": "https://www.inbenta.com/en/about-us/privacy-policy/", "date_range": ["2019-02", "2019-03"], "domains": ["inbenta.com"], "overview": {"reach": 0.000672447380064839, "site_reach_top10k": 33, "site_avg_frequency": 0.24280853638939887, "cookies": 0.21188748805149613, "bad_qs": 0.003226739131105827, "tracked": 0.2130717918588631, "https": 0.9994176229756997, "requests": 5.1113492523246205, "requests_tracking": 0.7401579826295249, "content_length": 42001.72286364866, "requests_failed": 1.1755043580528028, "has_blocking": 0.0, "script": 0.9829886230693327, "iframe": 0.015705658832015097, "beacon": 0.0, "image": 0.13387983483540647, "stylesheet": 0.7422683276416097, "font": 0.10777370433973776, "xhr": 0.1397663700933964, "plugin": 4.012845220444109e-05, "media": 0.001040252953299742, "referer_leaked": 0.9492261896799911, "referer_leaked_header": 0.9382124729518798, "referer_leaked_url": 0.0, "hosts": 1.0, "reach_rank": 656, "site_reach_rank": 661}, "reach_time_series": {"page": [0.0005452777924183719, 0.000672447380064839], "ts": ["2019-02", "2019-03"], "site": [29, 33]}, "presence_by_category": [["Business", 50.0], ["Banking", 41.666666666666664], ["News and Portals", 8.333333333333334]]}